klusta/__init__.py
klusta/conftest.py
klusta/datasets.py
klusta/klustakwik.py
klusta/launch.py
klusta/tempdir.py
klusta/utils.py
klusta/kwik/__init__.py
klusta/kwik/creator.py
klusta/kwik/h5.py
klusta/kwik/mea.py
klusta/kwik/mock.py
klusta/kwik/model.py
klusta/kwik/tests/__init__.py
klusta/kwik/tests/conftest.py
klusta/kwik/tests/test_creator.py
klusta/kwik/tests/test_h5.py
klusta/kwik/tests/test_mea.py
klusta/kwik/tests/test_mock.py
klusta/kwik/tests/test_model.py
klusta/probes/1x32_buzsaki.prb
klusta/tests/__init__.py
klusta/tests/test_datasets.py
klusta/tests/test_klustakwik.py
klusta/tests/test_launch.py
klusta/tests/test_tempdir.py
klusta/tests/test_utils.py
klusta/traces/__init__.py
klusta/traces/default_settings.py
klusta/traces/detect.py
klusta/traces/filter.py
klusta/traces/pca.py
klusta/traces/spikedetekt.py
klusta/traces/store.py
klusta/traces/waveform.py
klusta/traces/tests/__init__.py
klusta/traces/tests/test_detect.py
klusta/traces/tests/test_filter.py
klusta/traces/tests/test_pca.py
klusta/traces/tests/test_spikedetekt.py
klusta/traces/tests/test_store.py
klusta/traces/tests/test_waveform.py
klusta-3.0.16.dist-info/DESCRIPTION.rst
klusta-3.0.16.dist-info/METADATA
klusta-3.0.16.dist-info/RECORD
klusta-3.0.16.dist-info/WHEEL
klusta-3.0.16.dist-info/entry_points.txt
klusta-3.0.16.dist-info/metadata.json
klusta-3.0.16.dist-info/top_level.txt
