Metadata-Version: 1.1
Name: klusta
Version: 3.0.16
Summary: Spike detection and automatic clustering for spike sorting
Home-page: https://klusta.cortexlab.net
Author: Kwik Team
Author-email: cyrille.rossant at gmail.com
License: BSD
Keywords: klusta,neuroscience,spike sorting,klustakwik
Platform: UNKNOWN
Classifier: Development Status :: 3 - Alpha
Classifier: Intended Audience :: Science/Research
Classifier: License :: OSI Approved :: BSD License
Classifier: Natural Language :: English
Classifier: Programming Language :: Python :: 2
Classifier: Programming Language :: Python :: 2.7
Classifier: Programming Language :: Python :: 3
Classifier: Programming Language :: Python :: 3.4
Classifier: Programming Language :: Python :: 3.5
